Workbook

Sheet Mid-Year Review
B1: 2025 Mid-Year Review
A4: EMPLOYEE INFORMATION | D4: RATING SCALE
A5: Staff ID | B5: PAT00046 | D5: UNACCEPTABLE | E5: 1
A6: Name | B6: =INDEX('Staff list'!C:C,MATCH('Mid-Year Review'!B5,'Staff list'!B:B,0)) -> TOLUWANIMI AKINYEMI | D6: UNACCEPTABLE | E6: 2
A7: Department | B7: =INDEX('Staff list'!D:D,MATCH('Mid-Year Review'!B5,'Staff list'!B:B,0)) -> Technical (NOC) | D7: NEEDS IMPROVEMENT | E7: 3
A8: Unit | B8: =INDEX('Staff list'!D:D,MATCH('Mid-Year Review'!B5,'Staff list'!B:B,0)) -> Technical (NOC) | D8: MEETS EXPECTATION | E8: 4
A9: Role | B9: =INDEX('Staff list'!D:D,MATCH('Mid-Year Review'!B5,'Staff list'!B:B,0)) -> Technical (NOC) | D9: EXCEEDS EXPECTATION | E9: 5
A11: MID-YEAR REVIEW SCORE | B11: =F55 -> 0
A12: MID-YEAR REVIEW RATING | B12: =IF(B11>=101%, "Exceeds Expectation", IF(B11>=80%, "Meets Expectation", IF(B11>=60%, "Needs Improvement", "Unacceptable"))) -> Unacceptable
A15: PAT POLICY INFORMATION | B15: FINAL MID-YEAR/APPRAISAL SCORE IS SUBJECT TO MANAGEMENT REVIEW
A18: OBEJECTIVE, KEY RESULT (OKR) | B18: KEY RESULT AREA (KRA) | C18: WEIGHT | D18: EMPLOYEE SELF RATING | E18: MANAGER RATING | F18: SCORE
A19: {=_xlfn._xlws.FILTER(OKRs!F:F,OKRs!C:C='Mid-Year Review'!B6)} -> NOC Ticket closure rate-MTN | B19: {=_xlfn._xlws.FILTER(OKRs!J:J,OKRs!C:C='Mid-Year Review'!B6)} -> Ensure 70% Daily closure rate of MTN tickets | C19: {=_xlfn._xlws.FILTER(OKRs!H:H,OKRs!C:C='Mid-Year Review'!B6)} -> 0.3 | D19: 4 | F19: =E19/4*C19 -> 0
A20: RCA Accuracy of tickets which matches the on- field actual root causes and resolution (e.g., Trip Breaker for over 2.5 hours is unacceptable or Synchronization failure between Grid-DG, DG powered is not a correct RCA) | B20: Ensure 95% RCA accuracy rate of tickets which matches the on- field actual root causes and resolution | C20: 0.2 | D20: 5 | F20: =E20/4*C20 -> 0
A21: 65% and above sites meeting PA > 99.5% for MTN | B21: 65% and above sites meeting PA > 99.5% for MTN | C21: 0.15 | D21: 5 | F21: =E21/4*C21 -> 0
A22: Ensure average fault count <41 | B22: Ensure average fault count <41 | C22: 0.15 | D22: 5 | F22: =E22/4*C22 -> 0
A23: Ensure MTTR <90minutes | B23: Ensure MTTR <120minutes | C23: 0.1 | D23: 4 | F23: =E23/4*C23 -> 0
A24: Ensure reduction of Passive alarm count | B24: Ensure 1% Monthly reduction of Critical Passive alarm | C24: 0.1 | D24: 4 | F24: =E24/4*C24 -> 0
F25: =E25/4*C25 -> 0
F26: =E26/4*C26 -> 0
F27: =E27/4*C27 -> 0
F28: =E28/4*C28 -> 0
F29: =E29/4*C29 -> 0
F30: =E30/4*C30 -> 0
F31: =E31/4*C31 -> 0
F32: =E32/4*C32 -> 0
F33: =E33/4*C33 -> 0
F34: =E34/4*C34 -> 0
F35: =E35/4*C35 -> 0
F36: =E36/4*C36 -> 0
... F54: =E54/4*C54 -> 0
A55: Total | C55: =SUM(C19:C54) -> 1 | F55: =SUM(F19:F54) -> 0
A58: EMPLOYEE'S COMMENT | B58: I tried all my possible best to meet the expectations of the job given to me, all options of resolution were employed especially with the closure of active running tickets - calls (and follow-up calls) were made to the Huawei NOC and to their managers for the closure of the tickets. The 5-whys method were employed whenever RCAs are given to ascertain the exact root cause of a particular downtime. | C58: =INDEX(OKRs!C:C,MATCH('Mid-Year Review'!B5,OKRs!B:B,0)) -> TOLUWANIMI AKINYEMI
A59: MANAGER'S COMMENT | C59: =INDEX(OKRs!L:L,MATCH('Mid-Year Review'!B5,OKRs!B:B,0)) -> MURTALA ABDULMUMIN

Sheet OKRs
A1: S/N | B1: STAFF ID | C1: STAFF | D1: ROLE | E1: OKRs/KPIs | F1: OKRs 2 | G1: WEIGHT | H1: WEIGHT BROKENDOWN | I1: TARGET | J1: KEY RESULT AREA | K1: COMPANY RESULT | L1: LINE MANAGER
A2: 1 | B2: PAT00097 | C2: ADEJUMOKE AJALA | D2: Key Accounts Executive | E2: Reach commercial objectives | F2: Reach commercial objectives | G2: 0.5 | H2: 0.3 | I2: 80 | J2: Onboard 80 new BTS sites by Q4 2025, ensuring full operational readiness. | L2: ABIMBOLA FALOPE
A3: 1 | B3: PAT00097 | C3: ADEJUMOKE AJALA | D3: Key Accounts Executive | F3: Reach commercial objectives | H3: 0.2 | I3: 150 | J3: Onboard 150 new colo sites by Q4 2025, securing tenant commitments before launch. | L3: ABIMBOLA FALOPE
A4: 1 | B4: PAT00097 | C4: ADEJUMOKE AJALA | D4: Key Accounts Executive | E4: Increase revenue and strengthen commercial agreementsthrough contract renegotiation | F4: Increase revenue and strengthen commercial agreementsthrough contract renegotiation | G4: 0.2 | H4: 0.08 | I4: Nego | J4: Negotiate improved Airtel contract terms beyond the 2024 agreements by Q4 2025. | L4: ABIMBOLA FALOPE
A5: 1 | B5: PAT00097 | C5: ADEJUMOKE AJALA | D5: Key Accounts Executive | F5: Increase revenue and strengthen commercial agreementsthrough contract renegotiation | J5: Complete a full site audit by Q3 2025 to: | L5: ABIMBOLA FALOPE
A6: 1 | B6: PAT00097 | C6: ADEJUMOKE AJALA | D6: Key Accounts Executive | F6: Increase revenue and strengthen commercial agreementsthrough contract renegotiation | H6: 0.08 | I6: Iden | J6: Identify customer equipment across all sites. | L6: ABIMBOLA FALOPE
A7: 1 | B7: PAT00097 | C7: ADEJUMOKE AJALA | D7: Key Accounts Executive | F7: Increase revenue and strengthen commercial agreementsthrough contract renegotiation | H7: 0.04 | J7: Ensure full billing for underbilled sites. | L7: ABIMBOLA FALOPE
A8: 1 | B8: PAT00097 | C8: ADEJUMOKE AJALA | D8: Key Accounts Executive | E8: Enhance Billing Accuracy and Revenue Assurance | F8: Enhance Billing Accuracy and Revenue Assurance | G8: 0.1 | H8: 0.02 | I8: 1 | J8: Achieve 100% accuracy in invoice submissions by Q4 2025, including: | L8: ABIMBOLA FALOPE
A9: 1 | B9: PAT00097 | C9: ADEJUMOKE AJALA | D9: Key Accounts Executive | F9: Enhance Billing Accuracy and Revenue Assurance | H9: 0.07 | I9: 1 | J9: Full and optimal billing for excess power in favor of PAT. | L9: ABIMBOLA FALOPE
A10: 1 | B10: PAT00097 | C10: ADEJUMOKE AJALA | D10: Key Accounts Executive | F10: Enhance Billing Accuracy and Revenue Assurance | H10: 0.01 | I10: 1 | J10: Complete reconciliation of invoices for 100% of sites. | L10: ABIMBOLA FALOPE
A11: 1 | B11: PAT00097 | C11: ADEJUMOKE AJALA | D11: Key Accounts Executive | E11: Ensure high satisfaction from customers | F11: Ensure high satisfaction from customers | G11: 0.1 | H11: 0.075 | I11: 0.85 | J11: Achieve 85% customer satisfaction score through surveys and interviews by Q4 2025. | L11: ABIMBOLA FALOPE
A12: 1 | B12: PAT00097 | C12: ADEJUMOKE AJALA | D12: Key Accounts Executive | F12: Ensure high satisfaction from customers | H12: 0.025 | I12: 0.04 | J12: Conduct quarterly customer feedback sessions to identify areas for service improvement. | L12: ABIMBOLA FALOPE
A13: 1 | B13: PAT00097 | C13: ADEJUMOKE AJALA | D13: Key Accounts Executive | E13: Enhance Commercial Team Performance, Career Growth, and Retention | F13: Enhance Commercial Team Performance, Career Growth, and Retention | G13: 0.05 | H13: 0.02 | I13: 1 | J13: Ensure all commercial staff have OKRs set and aligned with business goals by the end of April 2025. | L13: ABIMBOLA FALOPE
A14: 1 | B14: PAT00097 | C14: ADEJUMOKE AJALA | D14: Key Accounts Executive | F14: Enhance Commercial Team Performance, Career Growth, and Retention | H14: 0.02 | I14: 1 | J14: Collaborate with HR to define a clear career roadmap for all non-field commercial positions and ensure 100% adoption within the team by Q3 2025. | L14: ABIMBOLA FALOPE
A15: 1 | B15: PAT00097 | C15: ADEJUMOKE AJALA | D15: Key Accounts Executive | F15: Enhance Commercial Team Performance, Career Growth, and Retention | H15: 0.01 | I15: Impl | J15: Implement strategies to retain top commercial talent, ensuring attrition of senior personnel does not exceed 5%. | L15: ABIMBOLA FALOPE
A16: 1 | B16: PAT00097 | C16: ADEJUMOKE AJALA | D16: Key Accounts Executive | E16: Ensure Seamless Commercial Integration and Business Continuity Post-ENL Acquisition | F16: Ensure Seamless Commercial Integration and Business Continuity Post-ENL Acquisition | G16: 0.05 | H16: 0.02 | I16: 1 | J16: Ensure a smooth transition of commercial contracts and agreements post-ENL acquisition, with 100% contract review and alignment completed by Q3 2025. | L16: ABIMBOLA FALOPE
A17: 1 | B17: PAT00097 | C17: ADEJUMOKE AJALA | D17: Key Accounts Executive | F17: Ensure Seamless Commercial Integration and Business Continuity Post-ENL Acquisition | H17: 0.01 | I17: 0 | J17: Work closely with Finance and Operations to consolidate and optimize ENL’s customer accounts, ensuring zero revenue leakage and streamlined billing processes. | L17: ABIMBOLA FALOPE
A18: 1 | B18: PAT00097 | C18: ADEJUMOKE AJALA | D18: Key Accounts Executive | F18: Ensure Seamless Commercial Integration and Business Continuity Post-ENL Acquisition | H18: 0.01 | I18: Impl | J18: Provide commercial input for ENL’s financial and operational integration plan, ensuring alignment with PAT’s revenue and growth targets. | L18: ABIMBOLA FALOPE
A19: 1 | B19: PAT00097 | C19: ADEJUMOKE AJALA | D19: Key Accounts Executive | F19: Ensure Seamless Commercial Integration and Business Continuity Post-ENL Acquisition | H19: 0.01 | I19: oversight | J19: Ensure commercial oversight in ENL’s business continuity strategy, mitigating customer churn and maintaining service quality during the transition. | L19: ABIMBOLA FALOPE
A20: 2 | B20: PAT00052 | C20: CAROLINE GBADAMOSI | D20: Key Accounts Manager | E20: Reach commercial objectives | F20: Reach commercial objectives | G20: 0.5 | H20: 0.3 | I20: 80 | J20: Onboard 80 new BTS sites by Q4 2025, ensuring full operational readiness. | L20: AJIBOLA OGUNBADEWA
A21: 2 | B21: PAT00052 | C21: CAROLINE GBADAMOSI | D21: Key Accounts Manager | F21: Reach commercial objectives | H21: 0.2 | I21: 150 | J21: Onboard 150 new colo sites by Q4 2025, securing tenant commitments before launch. | L21: AJIBOLA OGUNBADEWA
A22: 2 | B22: PAT00052 | C22: CAROLINE GBADAMOSI | D22: Key Accounts Manager | E22: Increase revenue and strengthen commercial agreementsthrough contract renegotiation | F22: Increase revenue and strengthen commercial agreementsthrough contract renegotiation | G22: 0.2 | H22: 0.09 | I22: 1 | J22: Successfully conclude MTN contract renegotiation by Q2 2025, ensuring improved financial and operational terms. | L22: AJIBOLA OGUNBADEWA
A23: 2 | B23: PAT00052 | C23: CAROLINE GBADAMOSI | D23: Key Accounts Manager | F23: Increase revenue and strengthen commercial agreementsthrough contract renegotiation | J23: Complete a full site audit by Q3 2025 to: | L23: AJIBOLA OGUNBADEWA
A24: 2 | B24: PAT00052 | C24: CAROLINE GBADAMOSI | D24: Key Accounts Manager | F24: Increase revenue and strengthen commercial agreementsthrough contract renegotiation | H24: 0.07 | I24: Iden | J24: Identify customer equipment across all sites. | L24: AJIBOLA OGUNBADEWA
A25: 2 | B25: PAT00052 | C25: CAROLINE GBADAMOSI | D25: Key Accounts Manager | F25: Increase revenue and strengthen commercial agreementsthrough contract renegotiation | H25: 0.04 | J25: Ensure full billing for underbilled sites. | L25: AJIBOLA OGUNBADEWA
A26: 2 | B26: PAT00052 | C26: CAROLINE GBADAMOSI | D26: Key Accounts Manager | E26: Enhance Billing Accuracy and Revenue Assurance | F26: Enhance Billing Accuracy and Revenue Assurance | G26: 0.1 | H26: 0.02 | I26: 1 | J26: Achieve 100% accuracy in invoice submissions by Q4 2025, including: | L26: AJIBOLA OGUNBADEWA
A27: 2 | B27: PAT00052 | C27: CAROLINE GBADAMOSI | D27: Key Accounts Manager | F27: Enhance Billing Accuracy and Revenue Assurance | H27: 0.07 | I27: 1 | J27: Full and optimal billing for excess power in favor of PAT. | L27: AJIBOLA OGUNBADEWA
A28: 2 | B28: PAT00052 | C28: CAROLINE GBADAMOSI | D28: Key Accounts Manager | F28: Enhance Billing Accuracy and Revenue Assurance | H28: 0.01 | I28: 1 | J28: Complete reconciliation of invoices for 100% of sites. | L28: AJIBOLA OGUNBADEWA
A29: 2 | B29: PAT00052 | C29: CAROLINE GBADAMOSI | D29: Key Accounts Manager | E29: Ensure high satisfaction from customers | F29: Ensure high satisfaction from customers | G29: 0.1 | H29: 0.075 | I29: 0.85 | J29: Achieve 85% customer satisfaction score through surveys and interviews by Q4 2025. | L29: AJIBOLA OGUNBADEWA
A30: 2 | B30: PAT00052 | C30: CAROLINE GBADAMOSI | D30: Key Accounts Manager | F30: Ensure high satisfaction from customers | H30: 0.025 | I30: 0.04 | J30: Conduct quarterly customer feedback sessions to identify areas for service improvement. | L30: AJIBOLA OGUNBADEWA
A31: 2 | B31: PAT00052 | C31: CAROLINE GBADAMOSI | D31: Key Accounts Manager | E31: Enhance Commercial Team Performance, Career Growth, and Retention | F31: Enhance Commercial Team Performance, Career Growth, and Retention | G31: 0.05 | H31: 0.03 | I31: 1 | J31: Ensure OKRs is set and aligned with business goals by the end of April 2025. | L31: AJIBOLA OGUNBADEWA
A32: 2 | B32: PAT00052 | C32: CAROLINE GBADAMOSI | D32: Key Accounts Manager | F32: Enhance Commercial Team Performance, Career Growth, and Retention | H32: 0.02 | I32: 1 | J32: Collaborate with HR to define a clear career roadmap for individual growth by Q3 2025. | L32: AJIBOLA OGUNBADEWA
A33: 2 | B33: PAT00052 | C33: CAROLINE GBADAMOSI | D33: Key Accounts Manager | E33: Ensure Seamless Commercial Integration and Business Continuity Post-ENL Acquisition | F33: Ensure Seamless Commercial Integration and Business Continuity Post-ENL Acquisition | G33: 0.05 | H33: 0.02 | I33: 1 | J33: Ensure a smooth transition of commercial contracts and agreements post-ENL acquisition, with 100% contract review and alignment completed by Q3 2025. | L33: AJIBOLA OGUNBADEWA
A34: 2 | B34: PAT00052 | C34: CAROLINE GBADAMOSI | D34: Key Accounts Manager | F34: Ensure Seamless Commercial Integration and Business Continuity Post-ENL Acquisition | H34: 0.01 | I34: 0 | J34: Work closely with Finance and Operations to consolidate and optimize ENL’s customer accounts, ensuring zero revenue leakage and streamlined billing processes. | L34: AJIBOLA OGUNBADEWA
A35: 2 | B35: PAT00052 | C35: CAROLINE GBADAMOSI | D35: Key Accounts Manager | F35: Ensure Seamless Commercial Integration and Business Continuity Post-ENL Acquisition | H35: 0.01 | I35: Impl | J35: Provide commercial input for ENL’s financial and operational integration plan, ensuring alignment with PAT’s revenue and growth targets. | L35: AJIBOLA OGUNBADEWA
A36: 2 | B36: PAT00052 | C36: CAROLINE GBADAMOSI | D36: Key Accounts Manager | F36: Ensure Seamless Commercial Integration and Business Continuity Post-ENL Acquisition | H36: 0.01 | I36: oversight | J36: Ensure commercial oversight in ENL’s business continuity strategy, mitigating customer churn and maintaining service quality during the transition. | L36: AJIBOLA OGUNBADEWA
A37: 3 | B37: PAT00029 | C37: ABOLAJI ANIMASHAUN | D37: Key Accounts Manager | E37: Reach commercial objectives | F37: Reach commercial objectives | G37: 0.5 | H37: 0.3 | I37: 80 | J37: Onboard 80 new BTS sites by Q4 2025, ensuring full operational readiness. | L37: AJIBOLA OGUNBADEWA
A38: 3 | B38: PAT00029 | C38: ABOLAJI ANIMASHAUN | D38: Key Accounts Manager | F38: Reach commercial objectives | H38: 0.2 | I38: 150 | J38: Onboard 150 new colo sites by Q4 2025, securing tenant commitments before launch. | L38: AJIBOLA OGUNBADEWA
A39: 3 | B39: PAT00029 | C39: ABOLAJI ANIMASHAUN | D39: Key Accounts Manager | E39: Increase revenue and strengthen commercial agreementsthrough contract renegotiation | F39: Increase revenue and strengthen commercial agreementsthrough contract renegotiation | G39: 0.2 | H39: 0.09 | I39: 1 | J39: Successfully conclude MTN contract renegotiation by Q2 2025, ensuring improved financial and operational terms. | L39: AJIBOLA OGUNBADEWA
A40: 3 | B40: PAT00029 | C40: ABOLAJI ANIMASHAUN | D40: Key Accounts Manager | F40: Increase revenue and strengthen commercial agreementsthrough contract renegotiation | J40: Complete a full site audit by Q3 2025 to: | L40: AJIBOLA OGUNBADEWA
A41: 3 | B41: PAT00029 | C41: ABOLAJI ANIMASHAUN | D41: Key Accounts Manager | F41: Increase revenue and strengthen commercial agreementsthrough contract renegotiation | H41: 0.07 | I41: Iden | J41: Identify customer equipment across all sites. | L41: AJIBOLA OGUNBADEWA
A42: 3 | B42: PAT00029 | C42: ABOLAJI ANIMASHAUN | D42: Key Accounts Manager | F42: Increase revenue and strengthen commercial agreementsthrough contract renegotiation | H42: 0.04 | J42: Ensure full billing for underbilled sites. | L42: AJIBOLA OGUNBADEWA
A43: 3 | B43: PAT00029 | C43: ABOLAJI ANIMASHAUN | D43: Key Accounts Manager | E43: Enhance Billing Accuracy and Revenue Assurance | F43: Enhance Billing Accuracy and Revenue Assurance | G43: 0.1 | H43: 0.02 | I43: 1 | J43: Achieve 100% accuracy in invoice submissions by Q4 2025, including: | L43: AJIBOLA OGUNBADEWA
A44: 3 | B44: PAT00029 | C44: ABOLAJI ANIMASHAUN | D44: Key Accounts Manager | F44: Enhance Billing Accuracy and Revenue Assurance | H44: 0.07 | I44: 1 | J44: Full and optimal billing for excess power in favor of PAT. | L44: AJIBOLA OGUNBADEWA
A45: 3 | B45: PAT00029 | C45: ABOLAJI ANIMASHAUN | D45: Key Accounts Manager | F45: Enhance Billing Accuracy and Revenue Assurance | H45: 0.01 | I45: 1 | J45: Complete reconciliation of invoices for 100% of sites. | L45: AJIBOLA OGUNBADEWA
A46: 3 | B46: PAT00029 | C46: ABOLAJI ANIMASHAUN | D46: Key Accounts Manager | E46: Ensure high satisfaction from customers | F46: Ensure high satisfaction from customers | G46: 0.1 | H46: 0.075 | I46: 0.85 | J46: Achieve 85% customer satisfaction score through surveys and interviews by Q4 2025. | L46: AJIBOLA OGUNBADEWA
A47: 3 | B47: PAT00029 | C47: ABOLAJI ANIMASHAUN | D47: Key Accounts Manager | F47: Ensure high satisfaction from customers | H47: 0.025 | I47: 0.04 | J47: Conduct quarterly customer feedback sessions to identify areas for service improvement. | L47: AJIBOLA OGUNBADEWA
A48: 3 | B48: PAT00029 | C48: ABOLAJI ANIMASHAUN | D48: Key Accounts Manager | E48: Enhance Commercial Team Performance, Career Growth, and Retention | F48: Enhance Commercial Team Performance, Career Growth, and Retention | G48: 0.05 | H48: 0.02 | I48: 1 | J48: Ensure all commercial staff have OKRs set and aligned with business goals by the end of April 2025. | L48: AJIBOLA OGUNBADEWA
A49: 3 | B49: PAT00029 | C49: ABOLAJI ANIMASHAUN | D49: Key Accounts Manager | F49: Enhance Commercial Team Performance, Career Growth, and Retention | H49: 0.02 | I49: 1 | J49: Collaborate with HR to define a clear career roadmap for all non-field commercial positions and ensure 100% adoption within the team by Q3 2025. | L49: AJIBOLA OGUNBADEWA
A50: 3 | B50: PAT00029 | C50: ABOLAJI ANIMASHAUN | D50: Key Accounts Manager | F50: Enhance Commercial Team Performance, Career Growth, and Retention | H50: 0.01 | I50: Impl | J50: Implement strategies to retain top commercial talent, ensuring attrition of senior personnel does not exceed 5%. | L50: AJIBOLA OGUNBADEWA
A51: 3 | B51: PAT00029 | C51: ABOLAJI ANIMASHAUN | D51: Key Accounts Manager | E51: Ensure Seamless Commercial Integration and Business Continuity Post-ENL Acquisition | F51: Ensure Seamless Commercial Integration and Business Continuity Post-ENL Acquisition | G51: 0.05 | H51: 0.02 | I51: 1 | J51: Ensure a smooth transition of commercial contracts and agreements post-ENL acquisition, with 100% contract review and alignment completed by Q3 2025. | L51: AJIBOLA OGUNBADEWA
A52: 3 | B52: PAT00029 | C52: ABOLAJI ANIMASHAUN | D52: Key Accounts Manager | F52: Ensure Seamless Commercial Integration and Business Continuity Post-ENL Acquisition | H52: 0.01 | I52: 0 | J52: Work closely with Finance and Operations to consolidate and optimize ENL’s customer accounts, ensuring zero revenue leakage and streamlined billing processes. | L52: AJIBOLA OGUNBADEWA
A53: 3 | B53: PAT00029 | C53: ABOLAJI ANIMASHAUN | D53: Key Accounts Manager | F53: Ensure Seamless Commercial Integration and Business Continuity Post-ENL Acquisition | H53: 0.01 | I53: Impl | J53: Provide commercial input for ENL’s financial and operational integration plan, ensuring alignment with PAT’s revenue and growth targets. | L53: AJIBOLA OGUNBADEWA
A54: 3 | B54: PAT00029 | C54: ABOLAJI ANIMASHAUN | D54: Key Accounts Manager | F54: Ensure Seamless Commercial Integration and Business Continuity Post-ENL Acquisition | H54: 0.01 | I54: oversight | J54: Ensure commercial oversight in ENL’s business continuity strategy, mitigating customer churn and maintaining service quality during the transition. | L54: AJIBOLA OGUNBADEWA
A55: 4 | B55: PAT00022 | C55: ABIMBOLA FALOPE | D55: Director Commercial | E55: Reach commercial objectives | F55: Reach commercial objectives | G55: 0.5 | H55: 0.3 | I55: 80 | J55: Onboard 80 new BTS sites by Q4 2025, ensuring full operational readiness. | L55: OLADIPO BADRU
A56: 4 | B56: PAT00022 | C56: ABIMBOLA FALOPE | D56: Director Commercial | F56: Reach commercial objectives | H56: 0.2 | I56: 150 | J56: Onboard 150 new colo sites by Q4 2025, securing tenant commitments before launch. | L56: OLADIPO BADRU
A57: 4 | B57: PAT00022 | C57: ABIMBOLA FALOPE | D57: Director Commercial | E57: Increase revenue and strengthen commercial agreementsthrough contract renegotiation | F57: Increase revenue and strengthen commercial agreementsthrough contract renegotiation | G57: 0.2 | H57: 0.075 | I57: 1 | J57: Successfully conclude MTN contract renegotiation by Q2 2025, ensuring improved financial and operational terms. | L57: OLADIPO BADRU
A58: 4 | B58: PAT00022 | C58: ABIMBOLA FALOPE | D58: Director Commercial | F58: Increase revenue and strengthen commercial agreementsthrough contract renegotiation | H58: 0.05 | I58: Nego | J58: Negotiate improved Airtel contract terms beyond the 2024 agreements by Q4 2025. | L58: OLADIPO BADRU
A59: 4 | B59: PAT00022 | C59: ABIMBOLA FALOPE | D59: Director Commercial | F59: Increase revenue and strengthen commercial agreementsthrough contract renegotiation | J59: Complete a full site audit by Q3 2025 to: | L59: OLADIPO BADRU
A60: 4 | B60: PAT00022 | C60: ABIMBOLA FALOPE | D60: Director Commercial | F60: Increase revenue and strengthen commercial agreementsthrough contract renegotiation | H60: 0.05 | I60: Iden | J60: Identify customer equipment across all sites. | L60: OLADIPO BADRU
A61: 4 | B61: PAT00022 | C61: ABIMBOLA FALOPE | D61: Director Commercial | F61: Increase revenue and strengthen commercial agreementsthrough contract renegotiation | H61: 0.025 | I61: 1 | J61: Ensure full billing for underbilled sites. | L61: OLADIPO BADRU
A62: 4 | B62: PAT00022 | C62: ABIMBOLA FALOPE | D62: Director Commercial | E62: Enhance Billing Accuracy and Revenue Assurance | F62: Enhance Billing Accuracy and Revenue Assurance | G62: 0.1 | H62: 0.02 | I62: 1 | J62: Achieve 100% accuracy in invoice submissions by Q4 2025, including: | L62: OLADIPO BADRU
A63: 4 | B63: PAT00022 | C63: ABIMBOLA FALOPE | D63: Director Commercial | F63: Enhance Billing Accuracy and Revenue Assurance | H63: 0.07 | I63: 1 | J63: Full and optimal billing for excess power in favor of PAT. | L63: OLADIPO BADRU
A64: 4 | B64: PAT00022 | C64: ABIMBOLA FALOPE | D64: Director Commercial | F64: Enhance Billing Accuracy and Revenue Assurance | H64: 0.01 | I64: 1 | J64: Complete reconciliation of invoices for 100% of sites. | L64: OLADIPO BADRU
A65: 4 | B65: PAT00022 | C65: ABIMBOLA FALOPE | D65: Director Commercial | E65: Ensure high satisfaction from customers | F65: Ensure high satisfaction from customers | G65: 0.1 | H65: 0.075 | I65: 0.85 | J65: Achieve 85% customer satisfaction score through surveys and interviews by Q4 2025. | L65: OLADIPO BADRU
A66: 4 | B66: PAT00022 | C66: ABIMBOLA FALOPE | D66: Director Commercial | F66: Ensure high satisfaction from customers | H66: 0.025 | I66: 0.04 | J66: Conduct quarterly customer feedback sessions to identify areas for service improvement. | L66: OLADIPO BADRU
A67: 4 | B67: PAT00022 | C67: ABIMBOLA FALOPE | D67: Director Commercial | E67: Enhance Commercial Team Performance, Career Growth, and Retention | F67: Enhance Commercial Team Performance, Career Growth, and Retention | G67: 0.05 | H67: 0.02 | I67: 1 | J67: Ensure all commercial staff have OKRs set and aligned with business goals by the end of April 2025. | L67: OLADIPO BADRU
A68: 4 | B68: PAT00022 | C68: ABIMBOLA FALOPE | D68: Director Commercial | F68: Enhance Commercial Team Performance, Career Growth, and Retention | H68: 0.02 | I68: 1 | J68: Collaborate with HR to define a clear career roadmap for all non-field commercial positions and ensure 100% adoption within the team by Q3 2025. | L68: OLADIPO BADRU
A69: 4 | B69: PAT00022 | C69: ABIMBOLA FALOPE | D69: Director Commercial | F69: Enhance Commercial Team Performance, Career Growth, and Retention | H69: 0.01 | I69: Impl | J69: Implement strategies to retain top commercial talent, ensuring attrition of senior personnel does not exceed 5%. | L69: OLADIPO BADRU
A70: 4 | B70: PAT00022 | C70: ABIMBOLA FALOPE | D70: Director Commercial | E70: Ensure Seamless Commercial Integration and Business Continuity Post-ENL Acquisition | F70: Ensure Seamless Commercial Integration and Business Continuity Post-ENL Acquisition | G70: 0.05 | H70: 0.02 | I70: 1 | J70: Ensure a smooth transition of commercial contracts and agreements post-ENL acquisition, with 100% contract review and alignment completed by Q3 2025. | L70: OLADIPO BADRU
A71: 4 | B71: PAT00022 | C71: ABIMBOLA FALOPE | D71: Director Commercial | F71: Ensure Seamless Commercial Integration and Business Continuity Post-ENL Acquisition | H71: 0.01 | I71: 0 | J71: Work closely with Finance and Operations to consolidate and optimize ENL’s customer accounts, ensuring zero revenue leakage and streamlined billing processes. | L71: OLADIPO BADRU
A72: 4 | B72: PAT00022 | C72: ABIMBOLA FALOPE | D72: Director Commercial | F72: Ensure Seamless Commercial Integration and Business Continuity Post-ENL Acquisition | H72: 0.01 | I72: Impl | J72: Provide commercial input for ENL’s financial and operational integration plan, ensuring alignment with PAT’s revenue and growth targets. | L72: OLADIPO BADRU
A73: 4 | B73: PAT00022 | C73: ABIMBOLA FALOPE | D73: Director Commercial | F73: Ensure Seamless Commercial Integration and Business Continuity Post-ENL Acquisition | H73: 0.01 | I73: oversight | J73: Ensure commercial oversight in ENL’s business continuity strategy, mitigating customer churn and maintaining service quality during the transition. | L73: OLADIPO BADRU
A74: 5 | B74: PAT00003 | C74: OMONIYI AKINOLA | D74: Senior Key Accounts Manager | E74: Reach commercial objectives | F74: Reach commercial objectives | G74: 0.5 | H74: 0.3 | I74: 80 | J74: Onboard 80 new BTS sites by Q4 2025, ensuring full operational readiness. | L74: ADEJUMOKE AJALA
A75: 5 | B75: PAT00003 | C75: OMONIYI AKINOLA | D75: Senior Key Accounts Manager | F75: Reach commercial objectives | H75: 0.2 | I75: 150 | J75: Onboard 150 new colo sites by Q4 2025, securing tenant commitments before launch. | L75: ADEJUMOKE AJALA
A76: 5 | B76: PAT00003 | C76: OMONIYI AKINOLA | D76: Senior Key Accounts Manager | E76: Increase revenue and strengthen commercial agreementsthrough contract renegotiation | F76: Increase revenue and strengthen commercial agreementsthrough contract renegotiation | G76: 0.2 | H76: 0.08 | I76: Nego | J76: Negotiate improved Airtel contract terms beyond the 2024 agreements by Q4 2025. | L76: ADEJUMOKE AJALA
A77: 5 | B77: PAT00003 | C77: OMONIYI AKINOLA | D77: Senior Key Accounts Manager | F77: Increase revenue and strengthen commercial agreementsthrough contract renegotiation | J77: Complete a full site audit by Q3 2025 to: | L77: ADEJUMOKE AJALA
A78: 5 | B78: PAT00003 | C78: OMONIYI AKINOLA | D78: Senior Key Accounts Manager | F78: Increase revenue and strengthen commercial agreementsthrough contract renegotiation | H78: 0.08 | I78: Iden | J78: Identify customer equipment across all sites. | L78: ADEJUMOKE AJALA
A79: 5 | B79: PAT00003 | C79: OMONIYI AKINOLA | D79: Senior Key Accounts Manager | F79: Increase revenue and strengthen commercial agreementsthrough contract renegotiation | H79: 0.04 | J79: Ensure full billing for underbilled sites. | L79: ADEJUMOKE AJALA
A80: 5 | B80: PAT00003 | C80: OMONIYI AKINOLA | D80: Senior Key Accounts Manager | E80: Enhance Billing Accuracy and Revenue Assurance | F80: Enhance Billing Accuracy and Revenue Assurance | G80: 0.1 | H80: 0.02 | I80: 1 | J80: Achieve 100% accuracy in invoice submissions by Q4 2025, including: | L80: ADEJUMOKE AJALA
A81: 5 | B81: PAT00003 | C81: OMONIYI AKINOLA | D81: Senior Key Accounts Manager | F81: Enhance Billing Accuracy and Revenue Assurance | H81: 0.07 | I81: 1 | J81: Full and optimal billing for excess power in favor of PAT. | L81: ADEJUMOKE AJALA
A82: 5 | B82: PAT00003 | C82: OMONIYI AKINOLA | D82: Senior Key Accounts Manager | F82: Enhance Billing Accuracy and Revenue Assurance | H82: 0.01 | I82: 1 | J82: Complete reconciliation of invoices for 100% of sites. | L82: ADEJUMOKE AJALA
A83: 5 | B83: PAT00003 | C83: OMONIYI AKINOLA | D83: Senior Key Accounts Manager | E83: Ensure high satisfaction from customers | F83: Ensure high satisfaction from customers | G83: 0.1 | H83: 0.075 | I83: 0.85 | J83: Achieve 85% customer satisfaction score through surveys and interviews by Q4 2025. | L83: ADEJUMOKE AJALA
A84: 5 | B84: PAT00003 | C84: OMONIYI AKINOLA | D84: Senior Key Accounts Manager | F84: Ensure high satisfaction from customers | H84: 0.025 | I84: 0.04 | J84: Conduct quarterly customer feedback sessions to identify areas for service improvement. | L84: ADEJUMOKE AJALA
A85: 5 | B85: PAT00003 | C85: OMONIYI AKINOLA | D85: Senior Key Accounts Manager | E85: Enhance Commercial Team Performance, Career Growth, and Retention | F85: Enhance Commercial Team Performance, Career Growth, and Retention | G85: 0.05 | H85: 0.02 | I85: 1 | J85: Ensure OKRs is set and aligned with business goals by the end of April 2025. | L85: ADEJUMOKE AJALA
A86: 5 | B86: PAT00003 | C86: OMONIYI AKINOLA | D86: Senior Key Accounts Manager | F86: Enhance Commercial Team Performance, Career Growth, and Retention | H86: 0.02 | I86: 1 | J86: Collalaborate with HR to define a clear career roadmap for individual growth by Q3 2025. | L86: ADEJUMOKE AJALA
A87: 5 | B87: PAT00003 | C87: OMONIYI AKINOLA | D87: Senior Key Accounts Manager | F87: Enhance Commercial Team Performance, Career Growth, and Retention | H87: 0.01 | I87: Impl | J87: Implement strategies to retain top commercial talent, ensuring attrition of junior personnel does not exceed 5%. | L87: ADEJUMOKE AJALA
A88: 5 | B88: PAT00003 | C88: OMONIYI AKINOLA | D88: Senior Key Accounts Manager | E88: Ensure Seamless Commercial Integration and Business Continuity Post-ENL Acquisition | F88: Ensure Seamless Commercial Integration and Business Continuity Post-ENL Acquisition | G88: 0.05 | H88: 0.02 | I88: 1 | J88: Ensure a smooth transition of commercial contracts and agreements post-ENL acquisition, with 100% contract review and alignment completed by Q3 2025. | L88: ADEJUMOKE AJALA
A89: 5 | B89: PAT00003 | C89: OMONIYI AKINOLA | D89: Senior Key Accounts Manager | F89: Ensure Seamless Commercial Integration and Business Continuity Post-ENL Acquisition | H89: 0.01 | I89: 0 | J89: Work closely with Finance and Operations to consolidate and optimize ENL’s customer accounts, ensuring zero revenue leakage and streamlined billing processes. | L89: ADEJUMOKE AJALA
A90: 5 | B90: PAT00003 | C90: OMONIYI AKINOLA | D90: Senior Key Accounts Manager | F90: Ensure Seamless Commercial Integration and Business Continuity Post-ENL Acquisition | H90: 0.01 | I90: Impl | J90: Provide commercial input for ENL’s financial and operational integration plan, ensuring alignment with PAT’s revenue and growth targets. | L90: ADEJUMOKE AJALA
A91: 5 | B91: PAT00003 | C91: OMONIYI AKINOLA | D91: Senior Key Accounts Manager | F91: Ensure Seamless Commercial Integration and Business Continuity Post-ENL Acquisition | H91: 0.01 | I91: oversight | J91: Ensure commercial oversight in ENL’s business continuity strategy, mitigating customer churn and maintaining service quality during the transition. | L91: ADEJUMOKE AJALA
A92: 6 | B92: PAT00020 | C92: NWABUKO KALU | D92: Radio Frequency Specialist | E92: Reach commercial objectives | F92: Reach commercial objectives | G92: 0.5 | H92: 0.3 | I92: 80 | J92: Onboard 80 new BTS sites by Q4 2025, ensuring full operational readiness. | L92: ABIMBOLA FALOPE
A93: 6 | B93: PAT00020 | C93: NWABUKO KALU | D93: Radio Frequency Specialist | F93: Reach commercial objectives | H93: 0.2 | I93: 150 | J93: Onboard 150 new colo sites by Q4 2025, securing tenant commitments before launch. | L93: ABIMBOLA FALOPE
A94: 6 | B94: PAT00020 | C94: NWABUKO KALU | D94: Radio Frequency Specialist | E94: Increase revenue and strengthen commercial agreementsthrough contract renegotiation | F94: Increase revenue and strengthen commercial agreementsthrough contract renegotiation | G94: 0.2 | H94: 0.04 | I94: 1 | J94: Successfully conclude MTN contract renegotiation by Q2 2025, ensuring improved financial and operational terms. | L94: ABIMBOLA FALOPE
A95: 6 | B95: PAT00020 | C95: NWABUKO KALU | D95: Radio Frequency Specialist | F95: Increase revenue and strengthen commercial agreementsthrough contract renegotiation | H95: 0.04 | I95: Nego | J95: Negotiate improved Airtel contract terms beyond the 2024 agreements by Q4 2025. | L95: ABIMBOLA FALOPE
A96: 6 | B96: PAT00020 | C96: NWABUKO KALU | D96: Radio Frequency Specialist | F96: Increase revenue and strengthen commercial agreementsthrough contract renegotiation | J96: Complete a full site audit by Q3 2025 to: | L96: ABIMBOLA FALOPE
A97: 6 | B97: PAT00020 | C97: NWABUKO KALU | D97: Radio Frequency Specialist | F97: Increase revenue and strengthen commercial agreementsthrough contract renegotiation | H97: 0.08 | I97: Iden | J97: Identify customer equipment across all sites. | L97: ABIMBOLA FALOPE
A98: 6 | B98: PAT00020 | C98: NWABUKO KALU | D98: Radio Frequency Specialist | F98: Increase revenue and strengthen commercial agreementsthrough contract renegotiation | H98: 0.04 | J98: Ensure full billing for underbilled sites. | L98: ABIMBOLA FALOPE
A99: 6 | B99: PAT00020 | C99: NWABUKO KALU | D99: Radio Frequency Specialist | E99: Enhance Billing Accuracy and Revenue Assurance | F99: Enhance Billing Accuracy and Revenue Assurance | G99: 0.1 | H99: 0.02 | I99: 1 | J99: Achieve 100% accuracy in invoice submissions by Q4 2025, including: | L99: ABIMBOLA FALOPE
A100: 6 | B100: PAT00020 | C100: NWABUKO KALU | D100: Radio Frequency Specialist | F100: Enhance Billing Accuracy and Revenue Assurance | H100: 0.07 | I100: 1 | J100: Full and optimal billing for excess power in favor of PAT. | L100: ABIMBOLA FALOPE
...

Sheet Staff list
A1: S/N | B1: Staff ID | C1: Name | D1: Dept | E1: Nomenclature | F1: LOCATION
A2: 1 | B2: PAT00107 | C2: OLADIPO BADRU | D2: Finance | E2: Chief Financial Officer | F2: HQ
A3: 2 | B3: PAT00015 | C3: ARUN PANDA | D3: Technical (CTO) | E3: Chief Technical Officer | F3: HQ
A4: 3 | B4: PAT00164 | C4: AJIBOLA OGUNBADEWA | D4: Commercial | E4: Key Accounts & RF Strategy Lead | F4: HQ
A5: 4 | B5: PAT00155 | C5: ABAYOMI ONITIJU | D5: IT | E5: Chief Information Officer | F5: HQ
A6: 5 | B6: PAT00097 | C6: ADEJUMOKE AJALA | D6: Commercial | E6: Key Accounts Executive | F6: HQ
A7: 6 | B7: PAT00113 | C7: ANTHONY OSAKWE | D7: Technical (DCTO Operations) | E7: Director Technical | F7: HQ
A8: 7 | B8: PAT00027 | C8: CHISOM NDUKWE | D8: HR/Admin | E8: Director, Human Resources & Admin | F8: HQ
A9: 8 | B9: PAT00022 | C9: ABIMBOLA FALOPE | D9: Commercial | E9: Director Commercial | F9: HQ
A10: 9 | B10: PAT00010 | C10: BABATUNDE OLANIYAN | D10: Legal | E10: Director of Legal | F10: HQ
A11: 10 | B11: PAT00110 | C11: SWAPNIL MAHADIK | D11: Technical (Operations) | E11: Head, Operations | F11: HQ
A12: 11 | B12: PAT00028 | C12: NNEAMAKA DIKE | D12: HR/Admin | E12: Head HR Business Partnering | F12: HQ
A13: 12 | B13: PAT00048 | C13: PAUL OBE | D13: IT | E13: IT Team lead | F13: HQ
... A114: 113 | B114: PAT00215 | C114: SIMON ITOK | D114: CEO's office | E114: Driver | F114: HQ

Sheet Sheet2
A1: 1
A2: 2
A3: 3
A4: 4
A5: 5

Sheet Sheet3
